Mbgdregressor/Mbgdregressor.py
Mbgdregressor/__init__.py
gdregressor/Mbgdregressor.py
gdregressor/__init__.py
Mbgdregressor-1.1.dist-info/LICENSE
Mbgdregressor-1.1.dist-info/METADATA
Mbgdregressor-1.1.dist-info/WHEEL
Mbgdregressor-1.1.dist-info/top_level.txt
Mbgdregressor-1.1.dist-info/RECORD
