Metadata-Version: 2.1
Name: Mbgdregressor
Version: 1.1
License-File: LICENSE
